xstatic/__init__.py
xstatic/pkg/__init__.py
xstatic/pkg/less/.DS_Store
xstatic/pkg/less/__init__.py
xstatic/pkg/less/data/.DS_Store
xstatic/pkg/less/data/js/.DS_Store
xstatic/pkg/less/data/js/less.min.js
xstatic_less-1.3.0.1.dist-info/METADATA
xstatic_less-1.3.0.1.dist-info/WHEEL
xstatic_less-1.3.0.1.dist-info/top_level.txt
xstatic_less-1.3.0.1.dist-info/RECORD
