Metadata-Version: 2.4
Name: XStatic-less
Version: 1.3.0.1
Summary: less 1.3.0 (XStatic packaging standard)
Home-page: http://lesscss.org/
Maintainer: Raphael Jasjukaitis
Maintainer-email: webmaster@raphaa.de
License: (same as less)
Keywords: less xstatic
Platform: any
Requires-Dist: xstatic
Dynamic: description
Dynamic: home-page
Dynamic: keywords
Dynamic: license
Dynamic: maintainer
Dynamic: maintainer-email
Dynamic: platform
Dynamic: requires-dist
Dynamic: summary
